code_audit/__init__.py
code_audit/admin.py
code_audit/code_audit.py
code_audit/models.py
code_audit/pylintrc
code_audit/utils.py
code_audit/api/__init__.py
code_audit/api/urls.py
code_audit/management/__init__.py
code_audit/management/commands/__init__.py
code_audit/management/commands/code_audit.py
code_audit/management/commands/code_audit_by_commend.py
code_audit/migrations/0001_initial.py
code_audit/migrations/0002_codeauditreport_created_at_and_more.py
code_audit/migrations/0003_codeauditreport_module_name_and_more.py
code_audit/migrations/0004_codeauditreportlog.py
code_audit/migrations/0005_alter_codeauditreport_file_name_and_more.py
code_audit/migrations/0006_codeauditreport_git_user.py
code_audit/migrations/__init__.py
django_code_audit-0.2.6.dist-info/licenses/LICENSE
django_code_audit-0.2.6.dist-info/METADATA
django_code_audit-0.2.6.dist-info/WHEEL
django_code_audit-0.2.6.dist-info/top_level.txt
django_code_audit-0.2.6.dist-info/RECORD
