Metadata-Version: 2.4
Name: django-code-audit
Version: 0.2.6
Summary: A Django app for auditing Python code using pylint
Home-page: https://github.com/ravikempanayaka/Code-Audit#
Author: Ravi K
Author-email: Ravi K <kravi2439@gmail.com>
License: MIT
Project-URL: Homepage, https://github.com/ravikempanayaka/Code-Audit#
Keywords: django,pylint,code audit,code quality,django admin,static analysis,linting,audit,python quality
Classifier: Framework :: Django
Classifier: Framework :: Django :: 4.0
Classifier: Framework :: Django :: 5.0
Classifier: Intended Audience :: Developers
Classifier: Topic :: Software Development :: Quality Assurance
Classifier: Topic :: Software Development :: Testing
Classifier: Programming Language :: Python :: 3
Requires-Python: >=3.8
License-File: LICENSE
Requires-Dist: Django>=4.0
Requires-Dist: pylint>=3.0
Requires-Dist: pylint-json2html
Requires-Dist: pylint-report
Dynamic: license-file
